oasis/__init__.py
oasis/apps.py
oasis/lib/__init__.py
oasis/lib/choices/__init__.py
oasis/lib/choices/customer_type.py
oasis/lib/managers/__init__.py
oasis/lib/managers/client.py
oasis/lib/managers/discount.py
oasis/lib/managers/oasis_product.py
oasis/lib/managers/product.py
oasis/lib/serializers/__init__.py
oasis/lib/serializers/product.py
oasis/migrations/0001_initial.py
oasis/migrations/__init__.py
oasis/models/__init__.py
oasis/models/local_models.py
oasis/models/oasis_models.py
oasis/tasks/__init__.py
oasis/tasks/load_products.py
cfhl_oasis4-1.0.1.dist-info/LICENSE
cfhl_oasis4-1.0.1.dist-info/METADATA
cfhl_oasis4-1.0.1.dist-info/WHEEL
cfhl_oasis4-1.0.1.dist-info/top_level.txt
cfhl_oasis4-1.0.1.dist-info/RECORD
