Metadata-Version: 2.1
Name: cfhl-oasis4
Version: 1.0.1
Summary: Cadefihuila OASIS4 interfaces
Author-email: Mario Cerón <mario.ceron@cqinversiones.co>
License: GNU GENERAL PUBLIC LICENSE
Keywords: django,cadefihuila
Classifier: License :: Other/Proprietary License
Classifier: Programming Language :: Python :: 3.9
Classifier: Development Status :: 5 - Production/Stable
Classifier: Framework :: Django
Classifier: Framework :: Django :: 4.1
Classifier: Environment :: Web Environment
Classifier: Operating System :: OS Independent
Classifier: Topic :: Internet :: WWW/HTTP
Requires-Python: >=3.9
License-File: LICENSE
Requires-Dist: Django (==4.1)
Requires-Dist: cx-Oracle
